django_model_admin_fields/__init__.py
django_model_admin_fields-0.3.1.dist-info/LICENSE.md
django_model_admin_fields-0.3.1.dist-info/METADATA
django_model_admin_fields-0.3.1.dist-info/WHEEL
django_model_admin_fields-0.3.1.dist-info/top_level.txt
django_model_admin_fields-0.3.1.dist-info/RECORD
