Metadata-Version: 2.1
Name: django_model_admin_fields
Version: 0.3.1
Summary: Django abstract model that adds admin fields (created_on/by, last_edited_on/by) to an existing model
Home-page: https://github.com/bernd-wechner/django-model-admin-fields
Author: Bernd Wechner
Author-email: bwechner@yahoo.com
Project-URL: Bug Tracker, https://github.com/bernd-wechner/django-model-admin-fields/issues
Classifier: Programming Language :: Python :: 3
Classifier: License :: Freely Distributable
Classifier: Operating System :: OS Independent
Classifier: Development Status :: 4 - Beta
Classifier: Framework :: Django :: 4.0
Classifier: Intended Audience :: System Administrators
Classifier: Topic :: Software Development :: Libraries :: Python Modules
Requires-Python: >=3.6
License-File: LICENSE.md
Requires-Dist: django-crequest
Requires-Dist: django-bitfield>=2.0.1
